compone/__init__.py
compone/component.py
compone/escape.py
compone/html/__init__.py
compone/html/component.py
compone/html/elements/__init__.py
compone/html/elements/content_sectioning.py
compone/html/elements/embedded.py
compone/html/elements/forms.py
compone/html/elements/inline_text.py
compone/html/elements/interactive.py
compone/html/elements/main.py
compone/html/elements/metadata.py
compone/html/elements/multimedia.py
compone/html/elements/other.py
compone/html/elements/scripting.py
compone/html/elements/table.py
compone/html/elements/text_content.py
compone/html/elements/web_components.py
compone/html/helpers.py
compone/htmx/__init__.py
compone/htmx/config.py
compone/htmx/constants.py
compone/robots/__init__.py
compone/robots/html_meta.py
compone/robots/robots_txt.py
compone/utils.py
compone/xml.py
compone-0.4.0.dist-info/METADATA
compone-0.4.0.dist-info/WHEEL
compone-0.4.0.dist-info/RECORD
